rpi_hw_info/__init__.py
rpi_hw_info/__main__.py
rpi_hw_info/detector.py
rpi_hw_info/models.py
rpi_hw_info-2.0.4.dist-info/LICENSE
rpi_hw_info-2.0.4.dist-info/METADATA
rpi_hw_info-2.0.4.dist-info/WHEEL
rpi_hw_info-2.0.4.dist-info/entry_points.txt
rpi_hw_info-2.0.4.dist-info/RECORD
