Metadata-Version: 2.3
Name: rpi-hw-info
Version: 2.0.4
Summary: Raspberry Pi Hardware Info Detector
License: GPL-3.0
Author: Original Author
Author-email: author@example.com
Requires-Python: >=3.8
Classifier: Programming Language :: Python :: 3
Classifier: Programming Language :: Python :: 3.8
Classifier: Programming Language :: Python :: 3.9
Classifier: Programming Language :: Python :: 3.10
Classifier: Programming Language :: Python :: 3.11
Classifier: Topic :: System :: Hardware
Classifier: Operating System :: POSIX :: Linux
Project-URL: Repository, https://github.com/username/rpi-hw-info
